Metadata-Version: 2.2
Name: musicpy
Version: 6.94
Summary: Musicpy is a music programming language in Python designed to write music in very handy syntax through music theory and algorithms.
Home-page: https://github.com/Rainbow-Dreamer/musicpy.git
Download-URL: https://github.com/Rainbow-Dreamer/musicpy/archive/6.94.tar.gz
Author: Rainbow-Dreamer
Author-email: 1036889495@qq.com
License: LGPLv2.1
Keywords: music language,use codes to write music,music language for AI
Classifier: Development Status :: 3 - Alpha
Classifier: Intended Audience :: Developers
Classifier: Topic :: Software Development :: Build Tools
Classifier: License :: OSI Approved :: GNU Lesser General Public License v2 or later (LGPLv2+)
Classifier: Programming Language :: Python :: 3.6
Classifier: Programming Language :: Python :: 3.7
Classifier: Programming Language :: Python :: 3.8
Classifier: Programming Language :: Python :: 3.9
Classifier: Programming Language :: Python :: 3.10
License-File: LICENSE
Requires-Dist: mido-fix
Requires-Dist: pygame-ce
Requires-Dist: dataclasses
Dynamic: author
Dynamic: author-email
Dynamic: classifier
Dynamic: description
Dynamic: description-content-type
Dynamic: download-url
Dynamic: home-page
Dynamic: keywords
Dynamic: license
Dynamic: requires-dist
Dynamic: summary
